{
    "backend": "api-server-nodejs",
    "db_name": "",
    "db_pass": "",
    "db_type": "sqlite",
    "db_user": "",
    "dbms": "1",
    "description": "generated product",
    "design": "horizon-ui",
    "docker": "1",
    "err_code": 0,
    "frontend": "react",
    "heroku": "0",
    "pattern": "fullstack",
    "pro": "0",
    "task_id": "06d9db70-00f2-445b-84d0-44aa3e015e83",
    "task_info": "Upload Sources [0%] - 184 files",
    "task_output": "06d9db70-00f2-445b-84d0-44aa3e015e83.zip",
    "task_result": "SUCCESS",
    "task_state": "RUNNING",
    "task_ts_end": "2022-12-12-01-54-01",
    "task_ts_start": "2022-12-12-01-54-00"
}